deepbots/__init__.py
deepbots/robots/__init__.py
deepbots/robots/controllers/__init__.py
deepbots/robots/controllers/csv_robot.py
deepbots/robots/controllers/emitter_receiver_robot.py
deepbots/supervisor/__init__.py
deepbots/supervisor/controllers/__init__.py
deepbots/supervisor/controllers/csv_supervisor_env.py
deepbots/supervisor/controllers/deepbots_supervisor_env.py
deepbots/supervisor/controllers/emitter_receiver_supervisor_env.py
deepbots/supervisor/controllers/robot_supervisor_env.py
deepbots/supervisor/wrappers/__init__.py
deepbots/supervisor/wrappers/keyboard_printer.py
deepbots/supervisor/wrappers/tensorboard_wrapper.py
deepbots-1.0.0.dist-info/LICENSE
deepbots-1.0.0.dist-info/METADATA
deepbots-1.0.0.dist-info/WHEEL
deepbots-1.0.0.dist-info/top_level.txt
deepbots-1.0.0.dist-info/RECORD
