Metadata-Version: 2.1
Name: deepbots
Version: 1.0.0
Summary: A wrapper framework for Reinforcement Learning in Webots     simulator
Author: aidudezzz
Author-email: deepbots@protonmail.com
License-File: LICENSE
